fhvite/__init__.py
fhvite/_modidx.py
fhvite/core.py
fhvite-0.0.1.dist-info/licenses/LICENSE
fhvite-0.0.1.dist-info/METADATA
fhvite-0.0.1.dist-info/WHEEL
fhvite-0.0.1.dist-info/entry_points.txt
fhvite-0.0.1.dist-info/top_level.txt
fhvite-0.0.1.dist-info/RECORD
